coc_token/__init__.py
coc_token-1.0.dist-info/LICENSE
coc_token-1.0.dist-info/METADATA
coc_token-1.0.dist-info/WHEEL
coc_token-1.0.dist-info/top_level.txt
coc_token-1.0.dist-info/RECORD
