Metadata-Version: 2.1
Name: coc-token
Version: 1.0
Summary: COC Auto Token Generator
Author: Nani
Author-email: dendukurisarma0@gmail.com
Classifier: Programming Language :: Python :: 3
Classifier: License :: OSI Approved :: MIT License
Classifier: Operating System :: OS Independent
License-File: LICENSE
